hayp/__init__.py
hayp/hayp.py
hayp/data/HandleJSON.py
hayp/data/LoadJSON.py
hayp/data/__init__.py
hayp/dynamism/PetriNetDraw.py
hayp/dynamism/PetriNetDynamism.py
hayp/dynamism/__init__.py
hayp/exception/HapyException.py
hayp/exception/__init__.py
hayp/logger/__init__.py
hayp/logger/logger.py
hayp/net/PetriNet.py
hayp/net/__init__.py
hayp-1.0.dist-info/METADATA
hayp-1.0.dist-info/WHEEL
hayp-1.0.dist-info/top_level.txt
hayp-1.0.dist-info/RECORD
