Metadata-Version: 2.1
Name: hayp
Version: 1.0
Summary: Libreria para modelar redes de Petri
Home-page: 
Author: Sebastian Yañez - Duver Hernandez - Georffrey Arevalo
Author-email: 
License: MIT
Requires-Dist: numpy
Requires-Dist: graphviz
